example.py
basic_math_ayush/__init__.py
basic_math_ayush/addition.py
basic_math_ayush/multiplication.py
basic_math_ayush/subtraction.py
basic_math_ayush-0.0.1.dist-info/LICENSE
basic_math_ayush-0.0.1.dist-info/METADATA
basic_math_ayush-0.0.1.dist-info/WHEEL
basic_math_ayush-0.0.1.dist-info/top_level.txt
basic_math_ayush-0.0.1.dist-info/RECORD
