Metadata-Version: 2.1
Name: basic_math_ayush
Version: 0.0.1
Summary: A small package to perform basic mathematical operations
Author-email: AyushCodez <Ayush.Gupta546@iiitb.ac.in>
Classifier: Programming Language :: Python :: 3
Classifier: License :: OSI Approved :: MIT License
Classifier: Operating System :: OS Independent
Requires-Python: >=3.8
License-File: LICENSE
